{
    "data": [
        {
            "assessment": "None",
            "crop": "0 0",
            "en_text": "P p",
            "en_trans": "",
            "en_headline_id": 0,
            "trans_headline_id": 0,
            "image": "thumbnail.jpg",
            "page_no": "0",
            "page_type": "meta",
            "page_type_id": 1,
            "sw_name": "Thumbnail",
            "skill": null,
            "trans_answer": "",
            "trans_en": "",
            "trans_text": "",
            "en_headline_audio": null,
            "trans_headline_audio": "",
            "en_headline_text": null,
            "trans_headline_text": null,
            "book_type": "letterbook",
            "book_meta": "{\n    \"set\": \"WB\",\n    \"path\": \"LB_PPX\",\n    \"content\": \"letter-book\",\n    \"wblevel\": {\n        \"EN\": 2,\n        \"ES\": 2,\n        \"ZH\": 2,\n        \"VI\": 2,\n        \"AR\": 2,\n        \"KO\": 2,\n        \"DA\": 2,\n        \"PS\": 2,\n        \"TL\": 2,\n        \"BN\": 2,\n        \"PT\": 2,\n        \"HK\": 2,\n        \"TW\": 2\n    },\n    \"title\": {\n        \"EN\": \"P p\",\n        \"ES\": \"P p\",\n        \"ZH\": \"P p\",\n        \"VI\": \"P p\",\n        \"AR\": \"P p\",\n        \"KO\": \"P p\",\n        \"DA\": \"P p\",\n        \"PS\": \"P p\",\n        \"TL\": \"P p\",\n        \"BN\": \"P p\",\n        \"PT\": \"P p\",\n        \"HK\": \"P p\",\n        \"TW\": \"P p\"\n    },\n    \"level\": {\n        \"EN\": 0,\n        \"ES\": 0,\n        \"ZH\": 0,\n        \"VI\": 0,\n        \"AR\": 0,\n        \"KO\": 0,\n        \"DA\": 0,\n        \"PS\": 0,\n        \"TL\": 0,\n        \"BN\": 0,\n        \"PT\": 0,\n        \"HK\": 0,\n        \"TW\": 0\n    },\n    \"lexile\": {\n        \"EN\": -1,\n        \"ES\": -1,\n        \"ZH\": -1,\n        \"VI\": -1,\n        \"AR\": -1,\n        \"KO\": -1,\n        \"DA\": -1,\n        \"PS\": -1,\n        \"TL\": -1,\n        \"BN\": -1,\n        \"PT\": -1,\n        \"HK\": -1,\n        \"TW\": -1\n    },\n    \"fp\": \"A\",\n    \"versions\": [\n        \"EN-ES\",\n        \"EN-AR\",\n        \"EN-BN\",\n        \"EN-KO\",\n        \"EN-PT\",\n        \"EN-TL\",\n        \"EN-VI\",\n        \"EN-ZH\"\n    ],\n    \"about\": \"Dummy About \\n\",\n    \"genre\": [],\n    \"subjects\": [],\n    \"grammar\": [],\n    \"keywords\": [],\n    \"mine\": true,\n    \"display\": \"normal\",\n    \"materials\": {\n        \"proficiency\": {},\n        \"activity\": {\n            \"EN\": \"DUMMY.pdf\",\n            \"ES\": \"DUMMY.pdf\",\n            \"ZH\": \"DUMMY.pdf\"\n        },\n        \"lesson_plan\": {\n            \"EN\": \"DUMMY.pdf\"\n        }\n    }\n}",
            "credit_data_en": null,
            "credit_data_trans": null
        },
        {
            "assessment": "None",
            "crop": "0 0",
            "en_text": "P p",
            "en_trans": "p p_p p",
            "en_headline_id": 0,
            "trans_headline_id": 0,
            "image": "LB_PPX_cover_p1.png",
            "page_no": "1",
            "page_type": "title",
            "page_type_id": 3,
            "sw_name": "Title",
            "skill": "read",
            "trans_answer": "",
            "trans_en": "p p_p p",
            "trans_text": "P p",
            "en_headline_audio": null,
            "trans_headline_audio": "",
            "en_headline_text": null,
            "trans_headline_text": null,
            "book_type": "letterbook",
            "book_meta": "{\n    \"set\": \"WB\",\n    \"path\": \"LB_PPX\",\n    \"content\": \"letter-book\",\n    \"wblevel\": {\n        \"EN\": 2,\n        \"ES\": 2,\n        \"ZH\": 2,\n        \"VI\": 2,\n        \"AR\": 2,\n        \"KO\": 2,\n        \"DA\": 2,\n        \"PS\": 2,\n        \"TL\": 2,\n        \"BN\": 2,\n        \"PT\": 2,\n        \"HK\": 2,\n        \"TW\": 2\n    },\n    \"title\": {\n        \"EN\": \"P p\",\n        \"ES\": \"P p\",\n        \"ZH\": \"P p\",\n        \"VI\": \"P p\",\n        \"AR\": \"P p\",\n        \"KO\": \"P p\",\n        \"DA\": \"P p\",\n        \"PS\": \"P p\",\n        \"TL\": \"P p\",\n        \"BN\": \"P p\",\n        \"PT\": \"P p\",\n        \"HK\": \"P p\",\n        \"TW\": \"P p\"\n    },\n    \"level\": {\n        \"EN\": 0,\n        \"ES\": 0,\n        \"ZH\": 0,\n        \"VI\": 0,\n        \"AR\": 0,\n        \"KO\": 0,\n        \"DA\": 0,\n        \"PS\": 0,\n        \"TL\": 0,\n        \"BN\": 0,\n        \"PT\": 0,\n        \"HK\": 0,\n        \"TW\": 0\n    },\n    \"lexile\": {\n        \"EN\": -1,\n        \"ES\": -1,\n        \"ZH\": -1,\n        \"VI\": -1,\n        \"AR\": -1,\n        \"KO\": -1,\n        \"DA\": -1,\n        \"PS\": -1,\n        \"TL\": -1,\n        \"BN\": -1,\n        \"PT\": -1,\n        \"HK\": -1,\n        \"TW\": -1\n    },\n    \"fp\": \"A\",\n    \"versions\": [\n        \"EN-ES\",\n        \"EN-AR\",\n        \"EN-BN\",\n        \"EN-KO\",\n        \"EN-PT\",\n        \"EN-TL\",\n        \"EN-VI\",\n        \"EN-ZH\"\n    ],\n    \"about\": \"Dummy About \\n\",\n    \"genre\": [],\n    \"subjects\": [],\n    \"grammar\": [],\n    \"keywords\": [],\n    \"mine\": true,\n    \"display\": \"normal\",\n    \"materials\": {\n        \"proficiency\": {},\n        \"activity\": {\n            \"EN\": \"DUMMY.pdf\",\n            \"ES\": \"DUMMY.pdf\",\n            \"ZH\": \"DUMMY.pdf\"\n        },\n        \"lesson_plan\": {\n            \"EN\": \"DUMMY.pdf\"\n        }\n    }\n}",
            "credit_data_en": null,
            "credit_data_trans": null,
            "en_vocab_audio": "EN_dictionary_1.mp3",
            "en_vocab_timecode": [
                {
                    "end": "2.76",
                    "word": "p p",
                    "start": "0"
                },
                {
                    "end": "2.76",
                    "word": "p p",
                    "start": "2.76"
                }
            ],
            "trans_vocab_audio": "ES_dictionary_1.mp3",
            "trans_vocab_timecode": [
                {
                    "end": "1.51",
                    "word": "p p",
                    "start": "0"
                },
                {
                    "end": "3.02",
                    "word": "p p",
                    "start": "1.51"
                }
            ],
            "nar_audio_en": "PPX_narr_Pp_p1.mp3",
            "nar_audio_trans": "ES_sample_1.mp3",
            "nar_timecode_trans": [
                {
                    "word": "p p",
                    "narrator": 0
                }
            ],
            "nar_timecode_en": [
                {
                    "word": "P P",
                    "narrator": 0
                }
            ]
        },
        {
            "assessment": "None",
            "crop": "0 0",
            "en_text": "pan",
            "en_trans": "pan_sartén",
            "en_headline_id": 0,
            "trans_headline_id": 0,
            "image": "LB_PPX_pan_p2.png",
            "page_no": "2",
            "page_type": "normal",
            "page_type_id": 2,
            "sw_name": "Story",
            "skill": "read",
            "trans_answer": "",
            "trans_en": "sartén_pan",
            "trans_text": "sartén",
            "en_headline_audio": null,
            "trans_headline_audio": "",
            "en_headline_text": null,
            "trans_headline_text": null,
            "book_type": "letterbook",
            "book_meta": "{\n    \"set\": \"WB\",\n    \"path\": \"LB_PPX\",\n    \"content\": \"letter-book\",\n    \"wblevel\": {\n        \"EN\": 2,\n        \"ES\": 2,\n        \"ZH\": 2,\n        \"VI\": 2,\n        \"AR\": 2,\n        \"KO\": 2,\n        \"DA\": 2,\n        \"PS\": 2,\n        \"TL\": 2,\n        \"BN\": 2,\n        \"PT\": 2,\n        \"HK\": 2,\n        \"TW\": 2\n    },\n    \"title\": {\n        \"EN\": \"P p\",\n        \"ES\": \"P p\",\n        \"ZH\": \"P p\",\n        \"VI\": \"P p\",\n        \"AR\": \"P p\",\n        \"KO\": \"P p\",\n        \"DA\": \"P p\",\n        \"PS\": \"P p\",\n        \"TL\": \"P p\",\n        \"BN\": \"P p\",\n        \"PT\": \"P p\",\n        \"HK\": \"P p\",\n        \"TW\": \"P p\"\n    },\n    \"level\": {\n        \"EN\": 0,\n        \"ES\": 0,\n        \"ZH\": 0,\n        \"VI\": 0,\n        \"AR\": 0,\n        \"KO\": 0,\n        \"DA\": 0,\n        \"PS\": 0,\n        \"TL\": 0,\n        \"BN\": 0,\n        \"PT\": 0,\n        \"HK\": 0,\n        \"TW\": 0\n    },\n    \"lexile\": {\n        \"EN\": -1,\n        \"ES\": -1,\n        \"ZH\": -1,\n        \"VI\": -1,\n        \"AR\": -1,\n        \"KO\": -1,\n        \"DA\": -1,\n        \"PS\": -1,\n        \"TL\": -1,\n        \"BN\": -1,\n        \"PT\": -1,\n        \"HK\": -1,\n        \"TW\": -1\n    },\n    \"fp\": \"A\",\n    \"versions\": [\n        \"EN-ES\",\n        \"EN-AR\",\n        \"EN-BN\",\n        \"EN-KO\",\n        \"EN-PT\",\n        \"EN-TL\",\n        \"EN-VI\",\n        \"EN-ZH\"\n    ],\n    \"about\": \"Dummy About \\n\",\n    \"genre\": [],\n    \"subjects\": [],\n    \"grammar\": [],\n    \"keywords\": [],\n    \"mine\": true,\n    \"display\": \"normal\",\n    \"materials\": {\n        \"proficiency\": {},\n        \"activity\": {\n            \"EN\": \"DUMMY.pdf\",\n            \"ES\": \"DUMMY.pdf\",\n            \"ZH\": \"DUMMY.pdf\"\n        },\n        \"lesson_plan\": {\n            \"EN\": \"DUMMY.pdf\"\n        }\n    }\n}",
            "credit_data_en": null,
            "credit_data_trans": null,
            "en_vocab_audio": "EN_dictionary_2.mp3",
            "en_vocab_timecode": [
                {
                    "end": "1.78",
                    "word": "pan",
                    "start": "0"
                },
                {
                    "end": "1.78",
                    "word": "pan",
                    "start": "1.78"
                }
            ],
            "trans_vocab_audio": "ES_dictionary_2.mp3",
            "trans_vocab_timecode": [
                {
                    "end": "1.588",
                    "word": "sartén",
                    "start": "0"
                },
                {
                    "end": "3.18",
                    "word": "sartén",
                    "start": "1.59"
                }
            ],
            "nar_audio_en": "PPX_narr_pan_p2.mp3",
            "nar_audio_trans": "ES_sample_2.mp3",
            "nar_timecode_trans": [
                {
                    "word": "sartén",
                    "narrator": 0
                }
            ],
            "nar_timecode_en": [
                {
                    "word": "pan",
                    "narrator": 0
                }
            ]
        },
        {
            "assessment": "None",
            "crop": "0 0",
            "en_text": "pet",
            "en_trans": "pet_mascota",
            "en_headline_id": 0,
            "trans_headline_id": 0,
            "image": "LB_PPX_pet_p3.png",
            "page_no": "3",
            "page_type": "normal",
            "page_type_id": 2,
            "sw_name": "Story",
            "skill": "read",
            "trans_answer": "",
            "trans_en": "mascota_pet",
            "trans_text": "mascota",
            "en_headline_audio": null,
            "trans_headline_audio": "",
            "en_headline_text": null,
            "trans_headline_text": null,
            "book_type": "letterbook",
            "book_meta": "{\n    \"set\": \"WB\",\n    \"path\": \"LB_PPX\",\n    \"content\": \"letter-book\",\n    \"wblevel\": {\n        \"EN\": 2,\n        \"ES\": 2,\n        \"ZH\": 2,\n        \"VI\": 2,\n        \"AR\": 2,\n        \"KO\": 2,\n        \"DA\": 2,\n        \"PS\": 2,\n        \"TL\": 2,\n        \"BN\": 2,\n        \"PT\": 2,\n        \"HK\": 2,\n        \"TW\": 2\n    },\n    \"title\": {\n        \"EN\": \"P p\",\n        \"ES\": \"P p\",\n        \"ZH\": \"P p\",\n        \"VI\": \"P p\",\n        \"AR\": \"P p\",\n        \"KO\": \"P p\",\n        \"DA\": \"P p\",\n        \"PS\": \"P p\",\n        \"TL\": \"P p\",\n        \"BN\": \"P p\",\n        \"PT\": \"P p\",\n        \"HK\": \"P p\",\n        \"TW\": \"P p\"\n    },\n    \"level\": {\n        \"EN\": 0,\n        \"ES\": 0,\n        \"ZH\": 0,\n        \"VI\": 0,\n        \"AR\": 0,\n        \"KO\": 0,\n        \"DA\": 0,\n        \"PS\": 0,\n        \"TL\": 0,\n        \"BN\": 0,\n        \"PT\": 0,\n        \"HK\": 0,\n        \"TW\": 0\n    },\n    \"lexile\": {\n        \"EN\": -1,\n        \"ES\": -1,\n        \"ZH\": -1,\n        \"VI\": -1,\n        \"AR\": -1,\n        \"KO\": -1,\n        \"DA\": -1,\n        \"PS\": -1,\n        \"TL\": -1,\n        \"BN\": -1,\n        \"PT\": -1,\n        \"HK\": -1,\n        \"TW\": -1\n    },\n    \"fp\": \"A\",\n    \"versions\": [\n        \"EN-ES\",\n        \"EN-AR\",\n        \"EN-BN\",\n        \"EN-KO\",\n        \"EN-PT\",\n        \"EN-TL\",\n        \"EN-VI\",\n        \"EN-ZH\"\n    ],\n    \"about\": \"Dummy About \\n\",\n    \"genre\": [],\n    \"subjects\": [],\n    \"grammar\": [],\n    \"keywords\": [],\n    \"mine\": true,\n    \"display\": \"normal\",\n    \"materials\": {\n        \"proficiency\": {},\n        \"activity\": {\n            \"EN\": \"DUMMY.pdf\",\n            \"ES\": \"DUMMY.pdf\",\n            \"ZH\": \"DUMMY.pdf\"\n        },\n        \"lesson_plan\": {\n            \"EN\": \"DUMMY.pdf\"\n        }\n    }\n}",
            "credit_data_en": null,
            "credit_data_trans": null,
            "en_vocab_audio": "EN_dictionary_3.mp3",
            "en_vocab_timecode": [
                {
                    "end": "1.57",
                    "word": "pet",
                    "start": "0"
                },
                {
                    "end": "1.57",
                    "word": "pet",
                    "start": "1.57"
                }
            ],
            "trans_vocab_audio": "ES_dictionary_3.mp3",
            "trans_vocab_timecode": [
                {
                    "end": "1.693",
                    "word": "mascota",
                    "start": "0"
                },
                {
                    "end": "3.38",
                    "word": "mascota",
                    "start": "1.69"
                }
            ],
            "nar_audio_en": "PPX_narr_pet_p3.mp3",
            "nar_audio_trans": "ES_sample_3.mp3",
            "nar_timecode_trans": [
                {
                    "word": "mascota",
                    "narrator": 0
                }
            ],
            "nar_timecode_en": [
                {
                    "word": "pet",
                    "narrator": 0
                }
            ]
        },
        {
            "assessment": "None",
            "crop": "0 0",
            "en_text": "pig",
            "en_trans": "pig_cerdo",
            "en_headline_id": 0,
            "trans_headline_id": 0,
            "image": "LB_PPX_pig_p4.png",
            "page_no": "4",
            "page_type": "normal",
            "page_type_id": 2,
            "sw_name": "Story",
            "skill": "read",
            "trans_answer": "",
            "trans_en": "cerdo_pig",
            "trans_text": "cerdo",
            "en_headline_audio": null,
            "trans_headline_audio": "",
            "en_headline_text": null,
            "trans_headline_text": null,
            "book_type": "letterbook",
            "book_meta": "{\n    \"set\": \"WB\",\n    \"path\": \"LB_PPX\",\n    \"content\": \"letter-book\",\n    \"wblevel\": {\n        \"EN\": 2,\n        \"ES\": 2,\n        \"ZH\": 2,\n        \"VI\": 2,\n        \"AR\": 2,\n        \"KO\": 2,\n        \"DA\": 2,\n        \"PS\": 2,\n        \"TL\": 2,\n        \"BN\": 2,\n        \"PT\": 2,\n        \"HK\": 2,\n        \"TW\": 2\n    },\n    \"title\": {\n        \"EN\": \"P p\",\n        \"ES\": \"P p\",\n        \"ZH\": \"P p\",\n        \"VI\": \"P p\",\n        \"AR\": \"P p\",\n        \"KO\": \"P p\",\n        \"DA\": \"P p\",\n        \"PS\": \"P p\",\n        \"TL\": \"P p\",\n        \"BN\": \"P p\",\n        \"PT\": \"P p\",\n        \"HK\": \"P p\",\n        \"TW\": \"P p\"\n    },\n    \"level\": {\n        \"EN\": 0,\n        \"ES\": 0,\n        \"ZH\": 0,\n        \"VI\": 0,\n        \"AR\": 0,\n        \"KO\": 0,\n        \"DA\": 0,\n        \"PS\": 0,\n        \"TL\": 0,\n        \"BN\": 0,\n        \"PT\": 0,\n        \"HK\": 0,\n        \"TW\": 0\n    },\n    \"lexile\": {\n        \"EN\": -1,\n        \"ES\": -1,\n        \"ZH\": -1,\n        \"VI\": -1,\n        \"AR\": -1,\n        \"KO\": -1,\n        \"DA\": -1,\n        \"PS\": -1,\n        \"TL\": -1,\n        \"BN\": -1,\n        \"PT\": -1,\n        \"HK\": -1,\n        \"TW\": -1\n    },\n    \"fp\": \"A\",\n    \"versions\": [\n        \"EN-ES\",\n        \"EN-AR\",\n        \"EN-BN\",\n        \"EN-KO\",\n        \"EN-PT\",\n        \"EN-TL\",\n        \"EN-VI\",\n        \"EN-ZH\"\n    ],\n    \"about\": \"Dummy About \\n\",\n    \"genre\": [],\n    \"subjects\": [],\n    \"grammar\": [],\n    \"keywords\": [],\n    \"mine\": true,\n    \"display\": \"normal\",\n    \"materials\": {\n        \"proficiency\": {},\n        \"activity\": {\n            \"EN\": \"DUMMY.pdf\",\n            \"ES\": \"DUMMY.pdf\",\n            \"ZH\": \"DUMMY.pdf\"\n        },\n        \"lesson_plan\": {\n            \"EN\": \"DUMMY.pdf\"\n        }\n    }\n}",
            "credit_data_en": null,
            "credit_data_trans": null,
            "en_vocab_audio": "EN_dictionary_4.mp3",
            "en_vocab_timecode": [
                {
                    "end": "1.78",
                    "word": "pig",
                    "start": "0"
                },
                {
                    "end": "1.78",
                    "word": "pig",
                    "start": "1.78"
                }
            ],
            "trans_vocab_audio": "ES_dictionary_4.mp3",
            "trans_vocab_timecode": [
                {
                    "end": "1.431",
                    "word": "cerdo",
                    "start": "0"
                },
                {
                    "end": "2.86",
                    "word": "cerdo",
                    "start": "1.43"
                }
            ],
            "nar_audio_en": "PPX_narr_pig_p4.mp3",
            "nar_audio_trans": "ES_sample_4.mp3",
            "nar_timecode_trans": [
                {
                    "word": "cerdo",
                    "narrator": 0
                }
            ],
            "nar_timecode_en": [
                {
                    "word": "pig",
                    "narrator": 0
                }
            ]
        },
        {
            "assessment": "None",
            "crop": "0 0",
            "en_text": "park",
            "en_trans": "park_parque",
            "en_headline_id": 0,
            "trans_headline_id": 0,
            "image": "LB_PPX_park_p5.png",
            "page_no": "5",
            "page_type": "normal",
            "page_type_id": 2,
            "sw_name": "Story",
            "skill": "read",
            "trans_answer": "",
            "trans_en": "parque_park",
            "trans_text": "parque",
            "en_headline_audio": null,
            "trans_headline_audio": "",
            "en_headline_text": null,
            "trans_headline_text": null,
            "book_type": "letterbook",
            "book_meta": "{\n    \"set\": \"WB\",\n    \"path\": \"LB_PPX\",\n    \"content\": \"letter-book\",\n    \"wblevel\": {\n        \"EN\": 2,\n        \"ES\": 2,\n        \"ZH\": 2,\n        \"VI\": 2,\n        \"AR\": 2,\n        \"KO\": 2,\n        \"DA\": 2,\n        \"PS\": 2,\n        \"TL\": 2,\n        \"BN\": 2,\n        \"PT\": 2,\n        \"HK\": 2,\n        \"TW\": 2\n    },\n    \"title\": {\n        \"EN\": \"P p\",\n        \"ES\": \"P p\",\n        \"ZH\": \"P p\",\n        \"VI\": \"P p\",\n        \"AR\": \"P p\",\n        \"KO\": \"P p\",\n        \"DA\": \"P p\",\n        \"PS\": \"P p\",\n        \"TL\": \"P p\",\n        \"BN\": \"P p\",\n        \"PT\": \"P p\",\n        \"HK\": \"P p\",\n        \"TW\": \"P p\"\n    },\n    \"level\": {\n        \"EN\": 0,\n        \"ES\": 0,\n        \"ZH\": 0,\n        \"VI\": 0,\n        \"AR\": 0,\n        \"KO\": 0,\n        \"DA\": 0,\n        \"PS\": 0,\n        \"TL\": 0,\n        \"BN\": 0,\n        \"PT\": 0,\n        \"HK\": 0,\n        \"TW\": 0\n    },\n    \"lexile\": {\n        \"EN\": -1,\n        \"ES\": -1,\n        \"ZH\": -1,\n        \"VI\": -1,\n        \"AR\": -1,\n        \"KO\": -1,\n        \"DA\": -1,\n        \"PS\": -1,\n        \"TL\": -1,\n        \"BN\": -1,\n        \"PT\": -1,\n        \"HK\": -1,\n        \"TW\": -1\n    },\n    \"fp\": \"A\",\n    \"versions\": [\n        \"EN-ES\",\n        \"EN-AR\",\n        \"EN-BN\",\n        \"EN-KO\",\n        \"EN-PT\",\n        \"EN-TL\",\n        \"EN-VI\",\n        \"EN-ZH\"\n    ],\n    \"about\": \"Dummy About \\n\",\n    \"genre\": [],\n    \"subjects\": [],\n    \"grammar\": [],\n    \"keywords\": [],\n    \"mine\": true,\n    \"display\": \"normal\",\n    \"materials\": {\n        \"proficiency\": {},\n        \"activity\": {\n            \"EN\": \"DUMMY.pdf\",\n            \"ES\": \"DUMMY.pdf\",\n            \"ZH\": \"DUMMY.pdf\"\n        },\n        \"lesson_plan\": {\n            \"EN\": \"DUMMY.pdf\"\n        }\n    }\n}",
            "credit_data_en": null,
            "credit_data_trans": null,
            "en_vocab_audio": "EN_dictionary_5.mp3",
            "en_vocab_timecode": [
                {
                    "end": "1.73",
                    "word": "park",
                    "start": "0"
                },
                {
                    "end": "1.73",
                    "word": "park",
                    "start": "1.73"
                }
            ],
            "trans_vocab_audio": "ES_dictionary_5.mp3",
            "trans_vocab_timecode": [
                {
                    "end": "1.51",
                    "word": "parque",
                    "start": "0"
                },
                {
                    "end": "3.02",
                    "word": "parque",
                    "start": "1.51"
                }
            ],
            "nar_audio_en": "PPX_narr_park_p5.mp3",
            "nar_audio_trans": "ES_sample_5.mp3",
            "nar_timecode_trans": [
                {
                    "word": "parque",
                    "narrator": 0
                }
            ],
            "nar_timecode_en": [
                {
                    "word": "park",
                    "narrator": 0
                }
            ]
        },
        {
            "assessment": "None",
            "crop": "0 0",
            "en_text": "pen",
            "en_trans": "pen_pluma",
            "en_headline_id": 0,
            "trans_headline_id": 0,
            "image": "LB_PPX_pen_p6.png",
            "page_no": "6",
            "page_type": "normal",
            "page_type_id": 2,
            "sw_name": "Story",
            "skill": "read",
            "trans_answer": "",
            "trans_en": "pluma_pen",
            "trans_text": "pluma",
            "en_headline_audio": null,
            "trans_headline_audio": "",
            "en_headline_text": null,
            "trans_headline_text": null,
            "book_type": "letterbook",
            "book_meta": "{\n    \"set\": \"WB\",\n    \"path\": \"LB_PPX\",\n    \"content\": \"letter-book\",\n    \"wblevel\": {\n        \"EN\": 2,\n        \"ES\": 2,\n        \"ZH\": 2,\n        \"VI\": 2,\n        \"AR\": 2,\n        \"KO\": 2,\n        \"DA\": 2,\n        \"PS\": 2,\n        \"TL\": 2,\n        \"BN\": 2,\n        \"PT\": 2,\n        \"HK\": 2,\n        \"TW\": 2\n    },\n    \"title\": {\n        \"EN\": \"P p\",\n        \"ES\": \"P p\",\n        \"ZH\": \"P p\",\n        \"VI\": \"P p\",\n        \"AR\": \"P p\",\n        \"KO\": \"P p\",\n        \"DA\": \"P p\",\n        \"PS\": \"P p\",\n        \"TL\": \"P p\",\n        \"BN\": \"P p\",\n        \"PT\": \"P p\",\n        \"HK\": \"P p\",\n        \"TW\": \"P p\"\n    },\n    \"level\": {\n        \"EN\": 0,\n        \"ES\": 0,\n        \"ZH\": 0,\n        \"VI\": 0,\n        \"AR\": 0,\n        \"KO\": 0,\n        \"DA\": 0,\n        \"PS\": 0,\n        \"TL\": 0,\n        \"BN\": 0,\n        \"PT\": 0,\n        \"HK\": 0,\n        \"TW\": 0\n    },\n    \"lexile\": {\n        \"EN\": -1,\n        \"ES\": -1,\n        \"ZH\": -1,\n        \"VI\": -1,\n        \"AR\": -1,\n        \"KO\": -1,\n        \"DA\": -1,\n        \"PS\": -1,\n        \"TL\": -1,\n        \"BN\": -1,\n        \"PT\": -1,\n        \"HK\": -1,\n        \"TW\": -1\n    },\n    \"fp\": \"A\",\n    \"versions\": [\n        \"EN-ES\",\n        \"EN-AR\",\n        \"EN-BN\",\n        \"EN-KO\",\n        \"EN-PT\",\n        \"EN-TL\",\n        \"EN-VI\",\n        \"EN-ZH\"\n    ],\n    \"about\": \"Dummy About \\n\",\n    \"genre\": [],\n    \"subjects\": [],\n    \"grammar\": [],\n    \"keywords\": [],\n    \"mine\": true,\n    \"display\": \"normal\",\n    \"materials\": {\n        \"proficiency\": {},\n        \"activity\": {\n            \"EN\": \"DUMMY.pdf\",\n            \"ES\": \"DUMMY.pdf\",\n            \"ZH\": \"DUMMY.pdf\"\n        },\n        \"lesson_plan\": {\n            \"EN\": \"DUMMY.pdf\"\n        }\n    }\n}",
            "credit_data_en": null,
            "credit_data_trans": null,
            "en_vocab_audio": "EN_dictionary_6.mp3",
            "en_vocab_timecode": [
                {
                    "end": "1.69",
                    "word": "pen",
                    "start": "0"
                },
                {
                    "end": "1.69",
                    "word": "pen",
                    "start": "1.69"
                }
            ],
            "trans_vocab_audio": "ES_dictionary_6.mp3",
            "trans_vocab_timecode": [
                {
                    "end": "1.379",
                    "word": "pluma",
                    "start": "0"
                },
                {
                    "end": "2.76",
                    "word": "pluma",
                    "start": "1.38"
                }
            ],
            "nar_audio_en": "PPX_narr_pen_p6.mp3",
            "nar_audio_trans": "ES_sample_6.mp3",
            "nar_timecode_trans": [
                {
                    "word": "pluma",
                    "narrator": 0
                }
            ],
            "nar_timecode_en": [
                {
                    "word": "pen",
                    "narrator": 0
                }
            ]
        },
        {
            "assessment": "None",
            "crop": "0 0",
            "en_text": "paper",
            "en_trans": "paper_papel",
            "en_headline_id": 0,
            "trans_headline_id": 0,
            "image": "LB_PPX_paper_p7.png",
            "page_no": "7",
            "page_type": "normal",
            "page_type_id": 2,
            "sw_name": "Story",
            "skill": "read",
            "trans_answer": "",
            "trans_en": "papel_paper",
            "trans_text": "papel",
            "en_headline_audio": null,
            "trans_headline_audio": "",
            "en_headline_text": null,
            "trans_headline_text": null,
            "book_type": "letterbook",
            "book_meta": "{\n    \"set\": \"WB\",\n    \"path\": \"LB_PPX\",\n    \"content\": \"letter-book\",\n    \"wblevel\": {\n        \"EN\": 2,\n        \"ES\": 2,\n        \"ZH\": 2,\n        \"VI\": 2,\n        \"AR\": 2,\n        \"KO\": 2,\n        \"DA\": 2,\n        \"PS\": 2,\n        \"TL\": 2,\n        \"BN\": 2,\n        \"PT\": 2,\n        \"HK\": 2,\n        \"TW\": 2\n    },\n    \"title\": {\n        \"EN\": \"P p\",\n        \"ES\": \"P p\",\n        \"ZH\": \"P p\",\n        \"VI\": \"P p\",\n        \"AR\": \"P p\",\n        \"KO\": \"P p\",\n        \"DA\": \"P p\",\n        \"PS\": \"P p\",\n        \"TL\": \"P p\",\n        \"BN\": \"P p\",\n        \"PT\": \"P p\",\n        \"HK\": \"P p\",\n        \"TW\": \"P p\"\n    },\n    \"level\": {\n        \"EN\": 0,\n        \"ES\": 0,\n        \"ZH\": 0,\n        \"VI\": 0,\n        \"AR\": 0,\n        \"KO\": 0,\n        \"DA\": 0,\n        \"PS\": 0,\n        \"TL\": 0,\n        \"BN\": 0,\n        \"PT\": 0,\n        \"HK\": 0,\n        \"TW\": 0\n    },\n    \"lexile\": {\n        \"EN\": -1,\n        \"ES\": -1,\n        \"ZH\": -1,\n        \"VI\": -1,\n        \"AR\": -1,\n        \"KO\": -1,\n        \"DA\": -1,\n        \"PS\": -1,\n        \"TL\": -1,\n        \"BN\": -1,\n        \"PT\": -1,\n        \"HK\": -1,\n        \"TW\": -1\n    },\n    \"fp\": \"A\",\n    \"versions\": [\n        \"EN-ES\",\n        \"EN-AR\",\n        \"EN-BN\",\n        \"EN-KO\",\n        \"EN-PT\",\n        \"EN-TL\",\n        \"EN-VI\",\n        \"EN-ZH\"\n    ],\n    \"about\": \"Dummy About \\n\",\n    \"genre\": [],\n    \"subjects\": [],\n    \"grammar\": [],\n    \"keywords\": [],\n    \"mine\": true,\n    \"display\": \"normal\",\n    \"materials\": {\n        \"proficiency\": {},\n        \"activity\": {\n            \"EN\": \"DUMMY.pdf\",\n            \"ES\": \"DUMMY.pdf\",\n            \"ZH\": \"DUMMY.pdf\"\n        },\n        \"lesson_plan\": {\n            \"EN\": \"DUMMY.pdf\"\n        }\n    }\n}",
            "credit_data_en": null,
            "credit_data_trans": null,
            "en_vocab_audio": "EN_dictionary_7.mp3",
            "en_vocab_timecode": [
                {
                    "end": "1.69",
                    "word": "paper",
                    "start": "0"
                },
                {
                    "end": "1.69",
                    "word": "paper",
                    "start": "1.69"
                }
            ],
            "trans_vocab_audio": "ES_dictionary_7.mp3",
            "trans_vocab_timecode": [
                {
                    "end": "1.457",
                    "word": "papel",
                    "start": "0"
                },
                {
                    "end": "2.92",
                    "word": "papel",
                    "start": "1.46"
                }
            ],
            "nar_audio_en": "PPX_narr_paper_p7.mp3",
            "nar_audio_trans": "ES_sample_7.mp3",
            "nar_timecode_trans": [
                {
                    "word": "papel",
                    "narrator": 0
                }
            ],
            "nar_timecode_en": [
                {
                    "word": "paper",
                    "narrator": 0
                }
            ]
        },
        {
            "assessment": "None",
            "crop": "10",
            "en_text": "What is this picture?",
            "en_trans": "paper_papel,pet_mascota,pen_pluma,pig_cerdo",
            "en_headline_id": 1,
            "trans_headline_id": 1,
            "image": "LB_PPX_pen_quiz.png",
            "page_no": "8",
            "page_type": "game-comprehension",
            "page_type_id": 4,
            "sw_name": "Comp-Vocab",
            "skill": "read",
            "trans_answer": "pen_pluma",
            "trans_en": "paper_papel,pet_mascota,pen_pluma,pig_cerdo",
            "trans_text": "",
            "en_headline_audio": "EN_headline_1.mp3",
            "trans_headline_audio": "ES_headline_1.mp3",
            "en_headline_text": "What is this picture?",
            "trans_headline_text": "¿Qué es esta imagen?",
            "book_type": "letterbook",
            "book_meta": "{\n    \"set\": \"WB\",\n    \"path\": \"LB_PPX\",\n    \"content\": \"letter-book\",\n    \"wblevel\": {\n        \"EN\": 2,\n        \"ES\": 2,\n        \"ZH\": 2,\n        \"VI\": 2,\n        \"AR\": 2,\n        \"KO\": 2,\n        \"DA\": 2,\n        \"PS\": 2,\n        \"TL\": 2,\n        \"BN\": 2,\n        \"PT\": 2,\n        \"HK\": 2,\n        \"TW\": 2\n    },\n    \"title\": {\n        \"EN\": \"P p\",\n        \"ES\": \"P p\",\n        \"ZH\": \"P p\",\n        \"VI\": \"P p\",\n        \"AR\": \"P p\",\n        \"KO\": \"P p\",\n        \"DA\": \"P p\",\n        \"PS\": \"P p\",\n        \"TL\": \"P p\",\n        \"BN\": \"P p\",\n        \"PT\": \"P p\",\n        \"HK\": \"P p\",\n        \"TW\": \"P p\"\n    },\n    \"level\": {\n        \"EN\": 0,\n        \"ES\": 0,\n        \"ZH\": 0,\n        \"VI\": 0,\n        \"AR\": 0,\n        \"KO\": 0,\n        \"DA\": 0,\n        \"PS\": 0,\n        \"TL\": 0,\n        \"BN\": 0,\n        \"PT\": 0,\n        \"HK\": 0,\n        \"TW\": 0\n    },\n    \"lexile\": {\n        \"EN\": -1,\n        \"ES\": -1,\n        \"ZH\": -1,\n        \"VI\": -1,\n        \"AR\": -1,\n        \"KO\": -1,\n        \"DA\": -1,\n        \"PS\": -1,\n        \"TL\": -1,\n        \"BN\": -1,\n        \"PT\": -1,\n        \"HK\": -1,\n        \"TW\": -1\n    },\n    \"fp\": \"A\",\n    \"versions\": [\n        \"EN-ES\",\n        \"EN-AR\",\n        \"EN-BN\",\n        \"EN-KO\",\n        \"EN-PT\",\n        \"EN-TL\",\n        \"EN-VI\",\n        \"EN-ZH\"\n    ],\n    \"about\": \"Dummy About \\n\",\n    \"genre\": [],\n    \"subjects\": [],\n    \"grammar\": [],\n    \"keywords\": [],\n    \"mine\": true,\n    \"display\": \"normal\",\n    \"materials\": {\n        \"proficiency\": {},\n        \"activity\": {\n            \"EN\": \"DUMMY.pdf\",\n            \"ES\": \"DUMMY.pdf\",\n            \"ZH\": \"DUMMY.pdf\"\n        },\n        \"lesson_plan\": {\n            \"EN\": \"DUMMY.pdf\"\n        }\n    }\n}",
            "credit_data_en": null,
            "credit_data_trans": null,
            "en_vocab_audio": "EN_choice_8.mp3",
            "trans_vocab_audio": "ES_choice_8.mp3",
            "en_vocab_timecode": [
                {
                    "end": "1.69",
                    "word": "paper",
                    "start": "0"
                },
                {
                    "end": "3.25",
                    "word": "pet",
                    "start": "1.69"
                },
                {
                    "end": "4.94",
                    "word": "pen",
                    "start": "3.25"
                },
                {
                    "end": "6.72",
                    "word": "pig",
                    "start": "4.94"
                }
            ],
            "trans_vocab_timecode": [
                {
                    "end": "1.457",
                    "word": "papel",
                    "start": "0"
                },
                {
                    "end": "3.15",
                    "word": "mascota",
                    "start": "1.457"
                },
                {
                    "end": "4.529",
                    "word": "pluma",
                    "start": "3.15"
                },
                {
                    "end": "5.96",
                    "word": "cerdo",
                    "start": "4.529"
                }
            ]
        },
        {
            "assessment": "None",
            "crop": "10",
            "en_text": "What is this picture?",
            "en_trans": "park_parque,paper_papel,pet_mascota,pig_cerdo",
            "en_headline_id": 1,
            "trans_headline_id": 1,
            "image": "LB_PPX_pet_quiz.png",
            "page_no": "9",
            "page_type": "game-comprehension",
            "page_type_id": 4,
            "sw_name": "Comp-Vocab",
            "skill": "read",
            "trans_answer": "pet_mascota",
            "trans_en": "park_parque,paper_papel,pet_mascota,pig_cerdo",
            "trans_text": "",
            "en_headline_audio": "EN_headline_1.mp3",
            "trans_headline_audio": "ES_headline_1.mp3",
            "en_headline_text": "What is this picture?",
            "trans_headline_text": "¿Qué es esta imagen?",
            "book_type": "letterbook",
            "book_meta": "{\n    \"set\": \"WB\",\n    \"path\": \"LB_PPX\",\n    \"content\": \"letter-book\",\n    \"wblevel\": {\n        \"EN\": 2,\n        \"ES\": 2,\n        \"ZH\": 2,\n        \"VI\": 2,\n        \"AR\": 2,\n        \"KO\": 2,\n        \"DA\": 2,\n        \"PS\": 2,\n        \"TL\": 2,\n        \"BN\": 2,\n        \"PT\": 2,\n        \"HK\": 2,\n        \"TW\": 2\n    },\n    \"title\": {\n        \"EN\": \"P p\",\n        \"ES\": \"P p\",\n        \"ZH\": \"P p\",\n        \"VI\": \"P p\",\n        \"AR\": \"P p\",\n        \"KO\": \"P p\",\n        \"DA\": \"P p\",\n        \"PS\": \"P p\",\n        \"TL\": \"P p\",\n        \"BN\": \"P p\",\n        \"PT\": \"P p\",\n        \"HK\": \"P p\",\n        \"TW\": \"P p\"\n    },\n    \"level\": {\n        \"EN\": 0,\n        \"ES\": 0,\n        \"ZH\": 0,\n        \"VI\": 0,\n        \"AR\": 0,\n        \"KO\": 0,\n        \"DA\": 0,\n        \"PS\": 0,\n        \"TL\": 0,\n        \"BN\": 0,\n        \"PT\": 0,\n        \"HK\": 0,\n        \"TW\": 0\n    },\n    \"lexile\": {\n        \"EN\": -1,\n        \"ES\": -1,\n        \"ZH\": -1,\n        \"VI\": -1,\n        \"AR\": -1,\n        \"KO\": -1,\n        \"DA\": -1,\n        \"PS\": -1,\n        \"TL\": -1,\n        \"BN\": -1,\n        \"PT\": -1,\n        \"HK\": -1,\n        \"TW\": -1\n    },\n    \"fp\": \"A\",\n    \"versions\": [\n        \"EN-ES\",\n        \"EN-AR\",\n        \"EN-BN\",\n        \"EN-KO\",\n        \"EN-PT\",\n        \"EN-TL\",\n        \"EN-VI\",\n        \"EN-ZH\"\n    ],\n    \"about\": \"Dummy About \\n\",\n    \"genre\": [],\n    \"subjects\": [],\n    \"grammar\": [],\n    \"keywords\": [],\n    \"mine\": true,\n    \"display\": \"normal\",\n    \"materials\": {\n        \"proficiency\": {},\n        \"activity\": {\n            \"EN\": \"DUMMY.pdf\",\n            \"ES\": \"DUMMY.pdf\",\n            \"ZH\": \"DUMMY.pdf\"\n        },\n        \"lesson_plan\": {\n            \"EN\": \"DUMMY.pdf\"\n        }\n    }\n}",
            "credit_data_en": null,
            "credit_data_trans": null,
            "en_vocab_audio": "EN_choice_9.mp3",
            "trans_vocab_audio": "ES_choice_9.mp3",
            "en_vocab_timecode": [
                {
                    "end": "1.73",
                    "word": "park",
                    "start": "0"
                },
                {
                    "end": "3.42",
                    "word": "paper",
                    "start": "1.73"
                },
                {
                    "end": "4.98",
                    "word": "pet",
                    "start": "3.42"
                },
                {
                    "end": "6.76",
                    "word": "pig",
                    "start": "4.98"
                }
            ],
            "trans_vocab_timecode": [
                {
                    "end": "1.51",
                    "word": "parque",
                    "start": "0"
                },
                {
                    "end": "2.967",
                    "word": "papel",
                    "start": "1.51"
                },
                {
                    "end": "4.66",
                    "word": "mascota",
                    "start": "2.967"
                },
                {
                    "end": "6.091",
                    "word": "cerdo",
                    "start": "4.66"
                }
            ]
        },
        {
            "assessment": "None",
            "crop": "10",
            "en_text": "What is this picture?",
            "en_trans": "pan_sartén,pig_cerdo,park_parque,pen_pluma",
            "en_headline_id": 1,
            "trans_headline_id": 1,
            "image": "LB_PPX_park_quiz.png",
            "page_no": "10",
            "page_type": "game-comprehension",
            "page_type_id": 4,
            "sw_name": "Comp-Vocab",
            "skill": "read",
            "trans_answer": "park_parque",
            "trans_en": "pan_sartén,pig_cerdo,park_parque,pen_pluma",
            "trans_text": "",
            "en_headline_audio": "EN_headline_1.mp3",
            "trans_headline_audio": "ES_headline_1.mp3",
            "en_headline_text": "What is this picture?",
            "trans_headline_text": "¿Qué es esta imagen?",
            "book_type": "letterbook",
            "book_meta": "{\n    \"set\": \"WB\",\n    \"path\": \"LB_PPX\",\n    \"content\": \"letter-book\",\n    \"wblevel\": {\n        \"EN\": 2,\n        \"ES\": 2,\n        \"ZH\": 2,\n        \"VI\": 2,\n        \"AR\": 2,\n        \"KO\": 2,\n        \"DA\": 2,\n        \"PS\": 2,\n        \"TL\": 2,\n        \"BN\": 2,\n        \"PT\": 2,\n        \"HK\": 2,\n        \"TW\": 2\n    },\n    \"title\": {\n        \"EN\": \"P p\",\n        \"ES\": \"P p\",\n        \"ZH\": \"P p\",\n        \"VI\": \"P p\",\n        \"AR\": \"P p\",\n        \"KO\": \"P p\",\n        \"DA\": \"P p\",\n        \"PS\": \"P p\",\n        \"TL\": \"P p\",\n        \"BN\": \"P p\",\n        \"PT\": \"P p\",\n        \"HK\": \"P p\",\n        \"TW\": \"P p\"\n    },\n    \"level\": {\n        \"EN\": 0,\n        \"ES\": 0,\n        \"ZH\": 0,\n        \"VI\": 0,\n        \"AR\": 0,\n        \"KO\": 0,\n        \"DA\": 0,\n        \"PS\": 0,\n        \"TL\": 0,\n        \"BN\": 0,\n        \"PT\": 0,\n        \"HK\": 0,\n        \"TW\": 0\n    },\n    \"lexile\": {\n        \"EN\": -1,\n        \"ES\": -1,\n        \"ZH\": -1,\n        \"VI\": -1,\n        \"AR\": -1,\n        \"KO\": -1,\n        \"DA\": -1,\n        \"PS\": -1,\n        \"TL\": -1,\n        \"BN\": -1,\n        \"PT\": -1,\n        \"HK\": -1,\n        \"TW\": -1\n    },\n    \"fp\": \"A\",\n    \"versions\": [\n        \"EN-ES\",\n        \"EN-AR\",\n        \"EN-BN\",\n        \"EN-KO\",\n        \"EN-PT\",\n        \"EN-TL\",\n        \"EN-VI\",\n        \"EN-ZH\"\n    ],\n    \"about\": \"Dummy About \\n\",\n    \"genre\": [],\n    \"subjects\": [],\n    \"grammar\": [],\n    \"keywords\": [],\n    \"mine\": true,\n    \"display\": \"normal\",\n    \"materials\": {\n        \"proficiency\": {},\n        \"activity\": {\n            \"EN\": \"DUMMY.pdf\",\n            \"ES\": \"DUMMY.pdf\",\n            \"ZH\": \"DUMMY.pdf\"\n        },\n        \"lesson_plan\": {\n            \"EN\": \"DUMMY.pdf\"\n        }\n    }\n}",
            "credit_data_en": null,
            "credit_data_trans": null,
            "en_vocab_audio": "EN_choice_10.mp3",
            "trans_vocab_audio": "ES_choice_10.mp3",
            "en_vocab_timecode": [
                {
                    "end": "1.78",
                    "word": "pan",
                    "start": "0"
                },
                {
                    "end": "3.56",
                    "word": "pig",
                    "start": "1.78"
                },
                {
                    "end": "5.29",
                    "word": "park",
                    "start": "3.56"
                },
                {
                    "end": "6.97",
                    "word": "pen",
                    "start": "5.29"
                }
            ],
            "trans_vocab_timecode": [
                {
                    "end": "1.588",
                    "word": "sartén",
                    "start": "0"
                },
                {
                    "end": "3.019",
                    "word": "cerdo",
                    "start": "1.588"
                },
                {
                    "end": "4.529",
                    "word": "parque",
                    "start": "3.019"
                },
                {
                    "end": "5.908",
                    "word": "pluma",
                    "start": "4.529"
                }
            ]
        },
        {
            "assessment": "None",
            "crop": "10",
            "en_text": "What is this picture?",
            "en_trans": "paper_papel,pig_cerdo,pan_sartén,pen_pluma",
            "en_headline_id": 1,
            "trans_headline_id": 1,
            "image": "LB_PPX_paper_quiz.png",
            "page_no": "11",
            "page_type": "game-comprehension",
            "page_type_id": 4,
            "sw_name": "Comp-Vocab",
            "skill": "read",
            "trans_answer": "paper_papel",
            "trans_en": "paper_papel,pig_cerdo,pan_sartén,pen_pluma",
            "trans_text": "",
            "en_headline_audio": "EN_headline_1.mp3",
            "trans_headline_audio": "ES_headline_1.mp3",
            "en_headline_text": "What is this picture?",
            "trans_headline_text": "¿Qué es esta imagen?",
            "book_type": "letterbook",
            "book_meta": "{\n    \"set\": \"WB\",\n    \"path\": \"LB_PPX\",\n    \"content\": \"letter-book\",\n    \"wblevel\": {\n        \"EN\": 2,\n        \"ES\": 2,\n        \"ZH\": 2,\n        \"VI\": 2,\n        \"AR\": 2,\n        \"KO\": 2,\n        \"DA\": 2,\n        \"PS\": 2,\n        \"TL\": 2,\n        \"BN\": 2,\n        \"PT\": 2,\n        \"HK\": 2,\n        \"TW\": 2\n    },\n    \"title\": {\n        \"EN\": \"P p\",\n        \"ES\": \"P p\",\n        \"ZH\": \"P p\",\n        \"VI\": \"P p\",\n        \"AR\": \"P p\",\n        \"KO\": \"P p\",\n        \"DA\": \"P p\",\n        \"PS\": \"P p\",\n        \"TL\": \"P p\",\n        \"BN\": \"P p\",\n        \"PT\": \"P p\",\n        \"HK\": \"P p\",\n        \"TW\": \"P p\"\n    },\n    \"level\": {\n        \"EN\": 0,\n        \"ES\": 0,\n        \"ZH\": 0,\n        \"VI\": 0,\n        \"AR\": 0,\n        \"KO\": 0,\n        \"DA\": 0,\n        \"PS\": 0,\n        \"TL\": 0,\n        \"BN\": 0,\n        \"PT\": 0,\n        \"HK\": 0,\n        \"TW\": 0\n    },\n    \"lexile\": {\n        \"EN\": -1,\n        \"ES\": -1,\n        \"ZH\": -1,\n        \"VI\": -1,\n        \"AR\": -1,\n        \"KO\": -1,\n        \"DA\": -1,\n        \"PS\": -1,\n        \"TL\": -1,\n        \"BN\": -1,\n        \"PT\": -1,\n        \"HK\": -1,\n        \"TW\": -1\n    },\n    \"fp\": \"A\",\n    \"versions\": [\n        \"EN-ES\",\n        \"EN-AR\",\n        \"EN-BN\",\n        \"EN-KO\",\n        \"EN-PT\",\n        \"EN-TL\",\n        \"EN-VI\",\n        \"EN-ZH\"\n    ],\n    \"about\": \"Dummy About \\n\",\n    \"genre\": [],\n    \"subjects\": [],\n    \"grammar\": [],\n    \"keywords\": [],\n    \"mine\": true,\n    \"display\": \"normal\",\n    \"materials\": {\n        \"proficiency\": {},\n        \"activity\": {\n            \"EN\": \"DUMMY.pdf\",\n            \"ES\": \"DUMMY.pdf\",\n            \"ZH\": \"DUMMY.pdf\"\n        },\n        \"lesson_plan\": {\n            \"EN\": \"DUMMY.pdf\"\n        }\n    }\n}",
            "credit_data_en": null,
            "credit_data_trans": null,
            "en_vocab_audio": "EN_choice_11.mp3",
            "trans_vocab_audio": "ES_choice_11.mp3",
            "en_vocab_timecode": [
                {
                    "end": "1.69",
                    "word": "paper",
                    "start": "0"
                },
                {
                    "end": "3.46",
                    "word": "pig",
                    "start": "1.69"
                },
                {
                    "end": "5.24",
                    "word": "pan",
                    "start": "3.46"
                },
                {
                    "end": "6.93",
                    "word": "pen",
                    "start": "5.24"
                }
            ],
            "trans_vocab_timecode": [
                {
                    "end": "1.457",
                    "word": "papel",
                    "start": "0"
                },
                {
                    "end": "2.889",
                    "word": "cerdo",
                    "start": "1.457"
                },
                {
                    "end": "4.477",
                    "word": "sartén",
                    "start": "2.889"
                },
                {
                    "end": "5.856",
                    "word": "pluma",
                    "start": "4.477"
                }
            ]
        },
        {
            "assessment": "None",
            "crop": "10",
            "en_text": "What is this picture?",
            "en_trans": "pan_sartén,pig_cerdo,pen_pluma,park_parque",
            "en_headline_id": 1,
            "trans_headline_id": 1,
            "image": "LB_PPX_pan_quiz.png",
            "page_no": "12",
            "page_type": "game-comprehension",
            "page_type_id": 4,
            "sw_name": "Comp-Vocab",
            "skill": "read",
            "trans_answer": "pan_sartén",
            "trans_en": "pan_sartén,pig_cerdo,pen_pluma,park_parque",
            "trans_text": "",
            "en_headline_audio": "EN_headline_1.mp3",
            "trans_headline_audio": "ES_headline_1.mp3",
            "en_headline_text": "What is this picture?",
            "trans_headline_text": "¿Qué es esta imagen?",
            "book_type": "letterbook",
            "book_meta": "{\n    \"set\": \"WB\",\n    \"path\": \"LB_PPX\",\n    \"content\": \"letter-book\",\n    \"wblevel\": {\n        \"EN\": 2,\n        \"ES\": 2,\n        \"ZH\": 2,\n        \"VI\": 2,\n        \"AR\": 2,\n        \"KO\": 2,\n        \"DA\": 2,\n        \"PS\": 2,\n        \"TL\": 2,\n        \"BN\": 2,\n        \"PT\": 2,\n        \"HK\": 2,\n        \"TW\": 2\n    },\n    \"title\": {\n        \"EN\": \"P p\",\n        \"ES\": \"P p\",\n        \"ZH\": \"P p\",\n        \"VI\": \"P p\",\n        \"AR\": \"P p\",\n        \"KO\": \"P p\",\n        \"DA\": \"P p\",\n        \"PS\": \"P p\",\n        \"TL\": \"P p\",\n        \"BN\": \"P p\",\n        \"PT\": \"P p\",\n        \"HK\": \"P p\",\n        \"TW\": \"P p\"\n    },\n    \"level\": {\n        \"EN\": 0,\n        \"ES\": 0,\n        \"ZH\": 0,\n        \"VI\": 0,\n        \"AR\": 0,\n        \"KO\": 0,\n        \"DA\": 0,\n        \"PS\": 0,\n        \"TL\": 0,\n        \"BN\": 0,\n        \"PT\": 0,\n        \"HK\": 0,\n        \"TW\": 0\n    },\n    \"lexile\": {\n        \"EN\": -1,\n        \"ES\": -1,\n        \"ZH\": -1,\n        \"VI\": -1,\n        \"AR\": -1,\n        \"KO\": -1,\n        \"DA\": -1,\n        \"PS\": -1,\n        \"TL\": -1,\n        \"BN\": -1,\n        \"PT\": -1,\n        \"HK\": -1,\n        \"TW\": -1\n    },\n    \"fp\": \"A\",\n    \"versions\": [\n        \"EN-ES\",\n        \"EN-AR\",\n        \"EN-BN\",\n        \"EN-KO\",\n        \"EN-PT\",\n        \"EN-TL\",\n        \"EN-VI\",\n        \"EN-ZH\"\n    ],\n    \"about\": \"Dummy About \\n\",\n    \"genre\": [],\n    \"subjects\": [],\n    \"grammar\": [],\n    \"keywords\": [],\n    \"mine\": true,\n    \"display\": \"normal\",\n    \"materials\": {\n        \"proficiency\": {},\n        \"activity\": {\n            \"EN\": \"DUMMY.pdf\",\n            \"ES\": \"DUMMY.pdf\",\n            \"ZH\": \"DUMMY.pdf\"\n        },\n        \"lesson_plan\": {\n            \"EN\": \"DUMMY.pdf\"\n        }\n    }\n}",
            "credit_data_en": null,
            "credit_data_trans": null,
            "en_vocab_audio": "EN_choice_12.mp3",
            "trans_vocab_audio": "ES_choice_12.mp3",
            "en_vocab_timecode": [
                {
                    "end": "1.78",
                    "word": "pan",
                    "start": "0"
                },
                {
                    "end": "3.56",
                    "word": "pig",
                    "start": "1.78"
                },
                {
                    "end": "5.24",
                    "word": "pen",
                    "start": "3.56"
                },
                {
                    "end": "6.97",
                    "word": "park",
                    "start": "5.24"
                }
            ],
            "trans_vocab_timecode": [
                {
                    "end": "1.588",
                    "word": "sartén",
                    "start": "0"
                },
                {
                    "end": "3.019",
                    "word": "cerdo",
                    "start": "1.588"
                },
                {
                    "end": "4.399",
                    "word": "pluma",
                    "start": "3.019"
                },
                {
                    "end": "5.908",
                    "word": "parque",
                    "start": "4.399"
                }
            ]
        },
        {
            "assessment": "None",
            "crop": "10",
            "en_text": "What is this picture?",
            "en_trans": "park_parque,pig_cerdo,paper_papel,pet_mascota",
            "en_headline_id": 1,
            "trans_headline_id": 1,
            "image": "LB_PPX_pig_quiz.png",
            "page_no": "13",
            "page_type": "game-comprehension",
            "page_type_id": 4,
            "sw_name": "Comp-Vocab",
            "skill": "read",
            "trans_answer": "pig_cerdo",
            "trans_en": "park_parque,pig_cerdo,paper_papel,pet_mascota",
            "trans_text": "",
            "en_headline_audio": "EN_headline_1.mp3",
            "trans_headline_audio": "ES_headline_1.mp3",
            "en_headline_text": "What is this picture?",
            "trans_headline_text": "¿Qué es esta imagen?",
            "book_type": "letterbook",
            "book_meta": "{\n    \"set\": \"WB\",\n    \"path\": \"LB_PPX\",\n    \"content\": \"letter-book\",\n    \"wblevel\": {\n        \"EN\": 2,\n        \"ES\": 2,\n        \"ZH\": 2,\n        \"VI\": 2,\n        \"AR\": 2,\n        \"KO\": 2,\n        \"DA\": 2,\n        \"PS\": 2,\n        \"TL\": 2,\n        \"BN\": 2,\n        \"PT\": 2,\n        \"HK\": 2,\n        \"TW\": 2\n    },\n    \"title\": {\n        \"EN\": \"P p\",\n        \"ES\": \"P p\",\n        \"ZH\": \"P p\",\n        \"VI\": \"P p\",\n        \"AR\": \"P p\",\n        \"KO\": \"P p\",\n        \"DA\": \"P p\",\n        \"PS\": \"P p\",\n        \"TL\": \"P p\",\n        \"BN\": \"P p\",\n        \"PT\": \"P p\",\n        \"HK\": \"P p\",\n        \"TW\": \"P p\"\n    },\n    \"level\": {\n        \"EN\": 0,\n        \"ES\": 0,\n        \"ZH\": 0,\n        \"VI\": 0,\n        \"AR\": 0,\n        \"KO\": 0,\n        \"DA\": 0,\n        \"PS\": 0,\n        \"TL\": 0,\n        \"BN\": 0,\n        \"PT\": 0,\n        \"HK\": 0,\n        \"TW\": 0\n    },\n    \"lexile\": {\n        \"EN\": -1,\n        \"ES\": -1,\n        \"ZH\": -1,\n        \"VI\": -1,\n        \"AR\": -1,\n        \"KO\": -1,\n        \"DA\": -1,\n        \"PS\": -1,\n        \"TL\": -1,\n        \"BN\": -1,\n        \"PT\": -1,\n        \"HK\": -1,\n        \"TW\": -1\n    },\n    \"fp\": \"A\",\n    \"versions\": [\n        \"EN-ES\",\n        \"EN-AR\",\n        \"EN-BN\",\n        \"EN-KO\",\n        \"EN-PT\",\n        \"EN-TL\",\n        \"EN-VI\",\n        \"EN-ZH\"\n    ],\n    \"about\": \"Dummy About \\n\",\n    \"genre\": [],\n    \"subjects\": [],\n    \"grammar\": [],\n    \"keywords\": [],\n    \"mine\": true,\n    \"display\": \"normal\",\n    \"materials\": {\n        \"proficiency\": {},\n        \"activity\": {\n            \"EN\": \"DUMMY.pdf\",\n            \"ES\": \"DUMMY.pdf\",\n            \"ZH\": \"DUMMY.pdf\"\n        },\n        \"lesson_plan\": {\n            \"EN\": \"DUMMY.pdf\"\n        }\n    }\n}",
            "credit_data_en": null,
            "credit_data_trans": null,
            "en_vocab_audio": "EN_choice_13.mp3",
            "trans_vocab_audio": "ES_choice_13.mp3",
            "en_vocab_timecode": [
                {
                    "end": "1.73",
                    "word": "park",
                    "start": "0"
                },
                {
                    "end": "3.51",
                    "word": "pig",
                    "start": "1.73"
                },
                {
                    "end": "5.2",
                    "word": "paper",
                    "start": "3.51"
                },
                {
                    "end": "6.76",
                    "word": "pet",
                    "start": "5.2"
                }
            ],
            "trans_vocab_timecode": [
                {
                    "end": "1.51",
                    "word": "parque",
                    "start": "0"
                },
                {
                    "end": "2.941",
                    "word": "cerdo",
                    "start": "1.51"
                },
                {
                    "end": "4.399",
                    "word": "papel",
                    "start": "2.941"
                },
                {
                    "end": "6.091",
                    "word": "mascota",
                    "start": "4.399"
                }
            ]
        },
        {
            "assessment": "None",
            "crop": "0 0",
            "en_text": "Cynthia Harrison Barbera||Translator||StoryWorld & Pixabay",
            "en_trans": "",
            "en_headline_id": 0,
            "trans_headline_id": 0,
            "image": "LB_PPX_cover_p1.png",
            "page_no": "14",
            "page_type": "credits",
            "page_type_id": 14,
            "sw_name": "Credits",
            "skill": null,
            "trans_answer": "",
            "trans_en": "",
            "trans_text": "",
            "en_headline_audio": null,
            "trans_headline_audio": "",
            "en_headline_text": null,
            "trans_headline_text": null,
            "book_type": "letterbook",
            "book_meta": "{\n    \"set\": \"WB\",\n    \"path\": \"LB_PPX\",\n    \"content\": \"letter-book\",\n    \"wblevel\": {\n        \"EN\": 2,\n        \"ES\": 2,\n        \"ZH\": 2,\n        \"VI\": 2,\n        \"AR\": 2,\n        \"KO\": 2,\n        \"DA\": 2,\n        \"PS\": 2,\n        \"TL\": 2,\n        \"BN\": 2,\n        \"PT\": 2,\n        \"HK\": 2,\n        \"TW\": 2\n    },\n    \"title\": {\n        \"EN\": \"P p\",\n        \"ES\": \"P p\",\n        \"ZH\": \"P p\",\n        \"VI\": \"P p\",\n        \"AR\": \"P p\",\n        \"KO\": \"P p\",\n        \"DA\": \"P p\",\n        \"PS\": \"P p\",\n        \"TL\": \"P p\",\n        \"BN\": \"P p\",\n        \"PT\": \"P p\",\n        \"HK\": \"P p\",\n        \"TW\": \"P p\"\n    },\n    \"level\": {\n        \"EN\": 0,\n        \"ES\": 0,\n        \"ZH\": 0,\n        \"VI\": 0,\n        \"AR\": 0,\n        \"KO\": 0,\n        \"DA\": 0,\n        \"PS\": 0,\n        \"TL\": 0,\n        \"BN\": 0,\n        \"PT\": 0,\n        \"HK\": 0,\n        \"TW\": 0\n    },\n    \"lexile\": {\n        \"EN\": -1,\n        \"ES\": -1,\n        \"ZH\": -1,\n        \"VI\": -1,\n        \"AR\": -1,\n        \"KO\": -1,\n        \"DA\": -1,\n        \"PS\": -1,\n        \"TL\": -1,\n        \"BN\": -1,\n        \"PT\": -1,\n        \"HK\": -1,\n        \"TW\": -1\n    },\n    \"fp\": \"A\",\n    \"versions\": [\n        \"EN-ES\",\n        \"EN-AR\",\n        \"EN-BN\",\n        \"EN-KO\",\n        \"EN-PT\",\n        \"EN-TL\",\n        \"EN-VI\",\n        \"EN-ZH\"\n    ],\n    \"about\": \"Dummy About \\n\",\n    \"genre\": [],\n    \"subjects\": [],\n    \"grammar\": [],\n    \"keywords\": [],\n    \"mine\": true,\n    \"display\": \"normal\",\n    \"materials\": {\n        \"proficiency\": {},\n        \"activity\": {\n            \"EN\": \"DUMMY.pdf\",\n            \"ES\": \"DUMMY.pdf\",\n            \"ZH\": \"DUMMY.pdf\"\n        },\n        \"lesson_plan\": {\n            \"EN\": \"DUMMY.pdf\"\n        }\n    }\n}",
            "credit_data_en": [
                "Written and Narrated by:Cynthia Harrison Barbera",
                "Translated by:Luis Montiel & Mafe Pulido Duarte",
                "Illustrated by:StoryWorld & Pixabay"
            ],
            "credit_data_trans": [
                "Escrito y narrado por:Cynthia Harrison Barbera",
                "Traducido por:Luis Montiel & Mafe Pulido Duarte",
                "Ilustrado por:StoryWorld & Pixabay"
            ],
            "book_name": "LB_PPX"
        }
    ]
}